avg/__init__.py
avg/avg.py
avg/examples/spinning_triangle.py
avg/examples/static_triangle.py
avg-1.0.2.dist-info/LICENSE.txt
avg-1.0.2.dist-info/METADATA
avg-1.0.2.dist-info/WHEEL
avg-1.0.2.dist-info/top_level.txt
avg-1.0.2.dist-info/RECORD
