Metadata-Version: 2.1
Name: avg
Version: 1.0.2
Summary: Animated Scalable Vector Graphics
Author-email: David Woodburn <david.woodburn@icloud.com>
License: MIT
Project-URL: Homepage, https://gitlab.com/davidwoodburn/avg
Project-URL: Bug Tracker, https://gitlab.com/davidwoodburn/avg/-/issues
Classifier: Programming Language :: Python :: 3
Classifier: License :: OSI Approved :: MIT License
Classifier: Operating System :: OS Independent
Requires-Python: >=3.6
License-File: LICENSE.txt
